{
	"list_of_aircraft_performance": [
		{
			"icaoDesignator": "B77L",
			"numberOfEngines": 2,
			"engineType": "JET",
			"wakeCategory": "H",
			"referenceMass": 280.01,
			"minimumMass": 145.15,
			"maximumMass": 347.45,
			"maximumPayloadMass": 63.957,
			"massGradient": 0.068924,
			"maxOperatingSpeed": 330.0,
			"maxOperatingMach": 0.89,
			"maxOperatingAltitude": 43100.0,
			"maximumAltitude": 35104.0,
			"temperatureGradient": -96.71,
			"wingSurfaceArea": 427.82,
			"buffetLiftCoefficient": 1.1743,
			"buffetingGradient": 0.50413,
			"image_path": "./assets/images/aircraft_image/b77.jpeg",
			"configurationAerodynamicsList": [
				{
					"name": "CLEAN",
					"stallSpeed": 171.0,
					"cD0": 0.023205,
					"cD2": 0.041138
				},
				{
					"name": "INITIAL_CLIMB",
					"stallSpeed": 141.0,
					"cD0": 0.014318,
					"cD2": 0.04904
				},
				{
					"name": "TAKE_OFF",
					"stallSpeed": 133.0,
					"cD0": 0.016957,
					"cD2": 0.04546
				},
				{
					"name": "APPROACH",
					"stallSpeed": 130.0,
					"cD0": 0.02207,
					"cD2": 0.043996
				},
				{
					"name": "LANDING",
					"stallSpeed": 118.0,
					"cD0": 0.10734,
					"cD2": 0.034209
				}
			],
			"cDIncreaseDueToGearDown": 0.0198,
			"cTc1": 579940.0,
			"cTc2": 57511.0,
			"cTc3": 1.2094e-11,
			"cTc4": 9.7222,
			"cTc5": 0.0082614,
			"cTdesLow": 0.11401,
			"cTdesHigh": -0.1017,
			"transitionAltitude": 37843.0,
			"cTdesApp": 0.086221,
			"cTdesLd": 0.37829,
			"referenceDescentSpeed": 310.0,
			"referenceDescentMach": 0.84,
			"cF1": 0.53638,
			"cF2": 861.36,
			"cF3": 34.579,
			"cF4": 63047.0,
			"cFcr": 0.85686,
			"takeOffLength": 3200.0,
			"landingLength": 1844.0,
			"wingspan": 64.8,
			"aircraftLength": 63.73,
			"runwayAccelerationMetresPerSecond": 2.57222222222222,
			"runwayDecelerationMetresPerSecond": 3.08666666666667,
			"airlineProcedureDefaultSpeeds": {
				"standardClimbCasBelow10000Feet": 310.0,
				"standardClimbCasAbove10000Feet": 310.0,
				"standardClimbMachNumber": 0.84,
				"standardDescentCasBelow10000Feet": 310.0,
				"standardDescentCasAbove10000Feet": 310.0,
				"standardDescentMachNumber": 0.84
			},
			"maxAccGlobalParameters": {
				"civilMaxLongAcc": 2.0,
				"civilMaxNormAcc": 5.0,
				"militaryMaxLongAcc": 0.0,
				"militaryMaxNormAcc": 0.0
			},
			"dragGlobalParameters": {
				"nominalBankAngleCivilToLd": 15.0,
				"nominalBankAngleCivilOther": 30.0,
				"nominalBankAngleMilitary": 50.0,
				"maximumBankAngleCivilToLd": 25.0,
				"maximumBankAngleCivilHolding": 35.0,
				"maximumBankAngleCivilOther": 45.0,
				"maximumBankAngleMilitary": 70.0,
				"expeditedDescentFactor": 1.6
			},
			"thrustGlobalParameters": {
				"takeOffThrustCoeff": 1.2,
				"maxCruiseThrustCoeff": 0.95
			},
			"configurationAltitudeThresholds": {
				"takeOffThreshold": 400.0,
				"initialClimbThreshold": 2000.0,
				"approachThreshold": 8000.0,
				"landingThreshold": 3000.0
			},
			"speedScheduleGlobalParameters": {
				"minSpeedCoeffTakeoff": 1.2,
				"minSpeedCoeffOthers": 1.3,
				"climbIncrement1Jet": 5.0,
				"climbIncrement2Jet": 10.0,
				"climbIncrement3Jet": 30.0,
				"climbIncrement4Jet": 60.0,
				"climbIncrement5Jet": 80.0,
				"climbIncrement6TurboPiston": 20.0,
				"climbIncrement7TurboPiston": 30.0,
				"climbIncrement8TurboPiston": 35.0,
				"descentIncrement1JetTurbo": 5.0,
				"descentIncrement2JetTurbo": 10.0,
				"descentIncrement3JetTurbo": 20.0,
				"descentIncrement4JetTurbo": 50.0,
				"descentIncrement5Piston": 5.0,
				"descentIncrement6Piston": 10.0,
				"descentIncrement7Piston": 20.0
			},
			"holdingSpeedGlobalParameters": {
				"holdingSpeedBelowFL140": 230.0,
				"holdingSpeedBetweenFL140AndFL200": 240.0,
				"holdingSpeedBetweenFL200AndFL340": 265.0,
				"holdingSpeedAboveFL340": 0.83
			},
			"groundSpeedGlobalParameters": {
				"runwayBacktrackSpeed": 35.0,
				"taxiSpeed": 15.0,
				"apronSpeed": 10.0,
				"gateSpeed": 5.0
			},
			"reducedPowerCoeffList": [
				{
					"type": "JET",
					"maximumReduction": 0.15
				},
				{
					"type": "TURBOPROP",
					"maximumReduction": 0.25
				},
				{
					"type": "PISTON",
					"maximumReduction": 0.0
				},
				{
					"type": "ELECTRIC",
					"maximumReduction": 0.0
				}
			]
		},
		{
			"icaoDesignator": "B77W",
			"numberOfEngines": 2,
			"engineType": "JET",
			"wakeCategory": "H",
			"referenceMass": 290.3,
			"minimumMass": 167.82,
			"maximumMass": 351.53,
			"maximumPayloadMass": 69.853,
			"massGradient": 0.070127,
			"maxOperatingSpeed": 330.0,
			"maxOperatingMach": 0.89,
			"maxOperatingAltitude": 43100.0,
			"maximumAltitude": 34314.0,
			"temperatureGradient": -108.1,
			"wingSurfaceArea": 427.82,
			"buffetLiftCoefficient": 1.1224,
			"buffetingGradient": 0.41465,
			"image_path": "./assets/images/aircraft_image/b77w.jpg",
			"configurationAerodynamicsList": [
				{
					"name": "CLEAN",
					"stallSpeed": 178.0,
					"cD0": 0.022913,
					"cD2": 0.042347
				},
				{
					"name": "INITIAL_CLIMB",
					"stallSpeed": 148.0,
					"cD0": 0.015336,
					"cD2": 0.048029
				},
				{
					"name": "TAKE_OFF",
					"stallSpeed": 139.0,
					"cD0": 0.01831,
					"cD2": 0.044843
				},
				{
					"name": "APPROACH",
					"stallSpeed": 135.0,
					"cD0": 0.024735,
					"cD2": 0.042193
				},
				{
					"name": "LANDING",
					"stallSpeed": 122.0,
					"cD0": 0.095207,
					"cD2": 0.036573
				}
			],
			"cDIncreaseDueToGearDown": 0.02515,
			"cTc1": 574190.0,
			"cTc2": 57932.0,
			"cTc3": 8.5249e-12,
			"cTc4": 9.715,
			"cTc5": 0.0087176,
			"cTdesLow": 0.10131,
			"cTdesHigh": -0.1569,
			"transitionAltitude": 37128.0,
			"cTdesApp": 0.088911,
			"cTdesLd": 0.39965,
			"referenceDescentSpeed": 310.0,
			"referenceDescentMach": 0.84,
			"cF1": 0.54124,
			"cF2": 858.42,
			"cF3": 34.6,
			"cF4": 62907.0,
			"cFcr": 0.86812,
			"takeOffLength": 3200.0,
			"landingLength": 1844.0,
			"wingspan": 64.8,
			"aircraftLength": 73.86,
			"runwayAccelerationMetresPerSecond": 2.57222222222222,
			"runwayDecelerationMetresPerSecond": 3.08666666666667,
			"airlineProcedureDefaultSpeeds": {
				"standardClimbCasBelow10000Feet": 310.0,
				"standardClimbCasAbove10000Feet": 310.0,
				"standardClimbMachNumber": 0.84,
				"standardDescentCasBelow10000Feet": 310.0,
				"standardDescentCasAbove10000Feet": 310.0,
				"standardDescentMachNumber": 0.84
			},
			"maxAccGlobalParameters": {
				"civilMaxLongAcc": 2.0,
				"civilMaxNormAcc": 5.0,
				"militaryMaxLongAcc": 0.0,
				"militaryMaxNormAcc": 0.0
			},
			"dragGlobalParameters": {
				"nominalBankAngleCivilToLd": 15.0,
				"nominalBankAngleCivilOther": 30.0,
				"nominalBankAngleMilitary": 50.0,
				"maximumBankAngleCivilToLd": 25.0,
				"maximumBankAngleCivilHolding": 35.0,
				"maximumBankAngleCivilOther": 45.0,
				"maximumBankAngleMilitary": 70.0,
				"expeditedDescentFactor": 1.6
			},
			"thrustGlobalParameters": {
				"takeOffThrustCoeff": 1.2,
				"maxCruiseThrustCoeff": 0.95
			},
			"configurationAltitudeThresholds": {
				"takeOffThreshold": 400.0,
				"initialClimbThreshold": 2000.0,
				"approachThreshold": 8000.0,
				"landingThreshold": 3000.0
			},
			"speedScheduleGlobalParameters": {
				"minSpeedCoeffTakeoff": 1.2,
				"minSpeedCoeffOthers": 1.3,
				"climbIncrement1Jet": 5.0,
				"climbIncrement2Jet": 10.0,
				"climbIncrement3Jet": 30.0,
				"climbIncrement4Jet": 60.0,
				"climbIncrement5Jet": 80.0,
				"climbIncrement6TurboPiston": 20.0,
				"climbIncrement7TurboPiston": 30.0,
				"climbIncrement8TurboPiston": 35.0,
				"descentIncrement1JetTurbo": 5.0,
				"descentIncrement2JetTurbo": 10.0,
				"descentIncrement3JetTurbo": 20.0,
				"descentIncrement4JetTurbo": 50.0,
				"descentIncrement5Piston": 5.0,
				"descentIncrement6Piston": 10.0,
				"descentIncrement7Piston": 20.0
			},
			"holdingSpeedGlobalParameters": {
				"holdingSpeedBelowFL140": 230.0,
				"holdingSpeedBetweenFL140AndFL200": 240.0,
				"holdingSpeedBetweenFL200AndFL340": 265.0,
				"holdingSpeedAboveFL340": 0.83
			},
			"groundSpeedGlobalParameters": {
				"runwayBacktrackSpeed": 35.0,
				"taxiSpeed": 15.0,
				"apronSpeed": 10.0,
				"gateSpeed": 5.0
			},
			"reducedPowerCoeffList": [
				{
					"type": "JET",
					"maximumReduction": 0.15
				},
				{
					"type": "TURBOPROP",
					"maximumReduction": 0.25
				},
				{
					"type": "PISTON",
					"maximumReduction": 0.0
				},
				{
					"type": "ELECTRIC",
					"maximumReduction": 0.0
				}
			]
		}
		
	]
}
